cohorts
