Metadata-Version: 1.2
Name: cohorts
Version: 0.7.3
Summary: Utilities for analyzing mutations and neoepitopes in patient cohorts
Home-page: https://github.com/tavinathanson/cohorts
Author: Tavi Nathanson
Author-email: tavi@hammerlab.org
License: http://www.apache.org/licenses/LICENSE-2.0.html
Platform: UNKNOWN
Classifier: Development Status :: 3 - Alpha
Classifier: Environment :: Console
Classifier: Operating System :: OS Independent
Classifier: Intended Audience :: Science/Research
Classifier: License :: OSI Approved :: Apache Software License
Classifier: Programming Language :: Python
Classifier: Topic :: Scientific/Engineering :: Bio-Informatics
Requires-Python: >=3.3
